taskue/__init__.py
taskue/cli.py
taskue/runner.py
taskue/task.py
taskue/utils.py
taskue/workflow.py
taskue-0.3.dist-info/LICENSE
taskue-0.3.dist-info/METADATA
taskue-0.3.dist-info/WHEEL
taskue-0.3.dist-info/entry_points.txt
taskue-0.3.dist-info/top_level.txt
taskue-0.3.dist-info/RECORD
