Metadata-Version: 2.1
Name: taskue
Version: 0.3
Summary: Multi stages task queue
Home-page: https://github.com/ahmedelsayed-93/taskue
Author: Ahmed El-Sayed
Author-email: ahmed.m.elsayed93@gmail.com
License: UNKNOWN
Platform: UNKNOWN
